{
    "AS_UWI_a3bf0cc3d72f487ab186ca5a21519d4b": {
        "id": "AS_UWI_a3bf0cc3d72f487ab186ca5a21519d4b",
        "type": "ACTION_SEQUENCE",
        "params": [],
        "contextObj": {
            "name": "uwuf6e3557d18e4dac8ff79ade6a3b1f25",
            "type": "userwidgets",
            "KUID": "uf6e3557d18e4dac8ff79ade6a3b1f25"
        },
        "language": "js",
        "actions": [{
            "id": "ADD_SNIPPET__ca22d751557e48e1904d2bfaf5d44796",
            "type": "ADD_SNIPPET",
            "codeSnippet": "this.loginSuccessEvent();",
            "parentId": null,
            "callbackType": null
        }]
    }
}